aiocrawler.py
pyaiocrawler-0.5.0.dist-info/LICENSE.md
pyaiocrawler-0.5.0.dist-info/METADATA
pyaiocrawler-0.5.0.dist-info/WHEEL
pyaiocrawler-0.5.0.dist-info/top_level.txt
pyaiocrawler-0.5.0.dist-info/zip-safe
pyaiocrawler-0.5.0.dist-info/RECORD
